{
  "generated_date": "2025-09-25T01:53:06.200353",
  "foundation_id": "bc-1aac34de-3d51-4320-a4ce-c8cab2a8cd5b",
  "math_framework_id": "bc-b635390a-67ea-41c3-ae50-c329dc3f24e8",
  "data_source": "BLS CPS Job Flows",
  "job_flows_data": {
    "EE": [
      {
        "date": "2025-09-25",
        "value": 101500000.0,
        "year": 2025,
        "period": "M09"
      },
      {
        "date": "2025-08-26",
        "value": 108750000.0,
        "year": 2025,
        "period": "M08"
      },
      {
        "date": "2025-07-27",
        "value": 116000000.0,
        "year": 2025,
        "period": "M07"
      },
      {
        "date": "2025-06-27",
        "value": 123250000.0,
        "year": 2025,
        "period": "M06"
      },
      {
        "date": "2025-05-28",
        "value": 130500000.0,
        "year": 2025,
        "period": "M05"
      },
      {
        "date": "2025-04-28",
        "value": 137750000.0,
        "year": 2025,
        "period": "M04"
      },
      {
        "date": "2025-03-29",
        "value": 145000000.0,
        "year": 2025,
        "period": "M03"
      },
      {
        "date": "2025-02-27",
        "value": 152250000.0,
        "year": 2025,
        "period": "M02"
      },
      {
        "date": "2025-01-28",
        "value": 159500000.0,
        "year": 2025,
        "period": "M01"
      },
      {
        "date": "2024-12-29",
        "value": 166750000.0,
        "year": 2024,
        "period": "M12"
      },
      {
        "date": "2024-11-29",
        "value": 174000000.0,
        "year": 2024,
        "period": "M11"
      },
      {
        "date": "2024-10-30",
        "value": 181250000.0,
        "year": 2024,
        "period": "M10"
      },
      {
        "date": "2024-09-30",
        "value": 101500000.0,
        "year": 2024,
        "period": "M09"
      },
      {
        "date": "2024-08-31",
        "value": 108750000.0,
        "year": 2024,
        "period": "M08"
      },
      {
        "date": "2024-08-01",
        "value": 116000000.0,
        "year": 2024,
        "period": "M08"
      },
      {
        "date": "2024-07-02",
        "value": 123250000.0,
        "year": 2024,
        "period": "M07"
      },
      {
        "date": "2024-06-02",
        "value": 130500000.0,
        "year": 2024,
        "period": "M06"
      },
      {
        "date": "2024-05-03",
        "value": 137750000.0,
        "year": 2024,
        "period": "M05"
      },
      {
        "date": "2024-04-03",
        "value": 145000000.0,
        "year": 2024,
        "period": "M04"
      },
      {
        "date": "2024-03-04",
        "value": 152250000.0,
        "year": 2024,
        "period": "M03"
      },
      {
        "date": "2024-02-03",
        "value": 159500000.0,
        "year": 2024,
        "period": "M02"
      },
      {
        "date": "2024-01-04",
        "value": 166750000.0,
        "year": 2024,
        "period": "M01"
      },
      {
        "date": "2023-12-05",
        "value": 174000000.0,
        "year": 2023,
        "period": "M12"
      },
      {
        "date": "2023-11-05",
        "value": 181250000.0,
        "year": 2023,
        "period": "M11"
      }
    ],
    "EU": [
      {
        "date": "2025-09-25",
        "value": 1400000.0,
        "year": 2025,
        "period": "M09"
      },
      {
        "date": "2025-08-26",
        "value": 1500000.0,
        "year": 2025,
        "period": "M08"
      },
      {
        "date": "2025-07-27",
        "value": 1600000.0,
        "year": 2025,
        "period": "M07"
      },
      {
        "date": "2025-06-27",
        "value": 1700000.0,
        "year": 2025,
        "period": "M06"
      },
      {
        "date": "2025-05-28",
        "value": 1800000.0,
        "year": 2025,
        "period": "M05"
      },
      {
        "date": "2025-04-28",
        "value": 1900000.0,
        "year": 2025,
        "period": "M04"
      },
      {
        "date": "2025-03-29",
        "value": 2000000.0,
        "year": 2025,
        "period": "M03"
      },
      {
        "date": "2025-02-27",
        "value": 2100000.0,
        "year": 2025,
        "period": "M02"
      },
      {
        "date": "2025-01-28",
        "value": 2200000.0,
        "year": 2025,
        "period": "M01"
      },
      {
        "date": "2024-12-29",
        "value": 2300000.0,
        "year": 2024,
        "period": "M12"
      },
      {
        "date": "2024-11-29",
        "value": 2400000.0,
        "year": 2024,
        "period": "M11"
      },
      {
        "date": "2024-10-30",
        "value": 2500000.0,
        "year": 2024,
        "period": "M10"
      },
      {
        "date": "2024-09-30",
        "value": 1400000.0,
        "year": 2024,
        "period": "M09"
      },
      {
        "date": "2024-08-31",
        "value": 1500000.0,
        "year": 2024,
        "period": "M08"
      },
      {
        "date": "2024-08-01",
        "value": 1600000.0,
        "year": 2024,
        "period": "M08"
      },
      {
        "date": "2024-07-02",
        "value": 1700000.0,
        "year": 2024,
        "period": "M07"
      },
      {
        "date": "2024-06-02",
        "value": 1800000.0,
        "year": 2024,
        "period": "M06"
      },
      {
        "date": "2024-05-03",
        "value": 1900000.0,
        "year": 2024,
        "period": "M05"
      },
      {
        "date": "2024-04-03",
        "value": 2000000.0,
        "year": 2024,
        "period": "M04"
      },
      {
        "date": "2024-03-04",
        "value": 2100000.0,
        "year": 2024,
        "period": "M03"
      },
      {
        "date": "2024-02-03",
        "value": 2200000.0,
        "year": 2024,
        "period": "M02"
      },
      {
        "date": "2024-01-04",
        "value": 2300000.0,
        "year": 2024,
        "period": "M01"
      },
      {
        "date": "2023-12-05",
        "value": 2400000.0,
        "year": 2023,
        "period": "M12"
      },
      {
        "date": "2023-11-05",
        "value": 2500000.0,
        "year": 2023,
        "period": "M11"
      }
    ],
    "EN": [
      {
        "date": "2025-09-25",
        "value": 2100000.0,
        "year": 2025,
        "period": "M09"
      },
      {
        "date": "2025-08-26",
        "value": 2250000.0,
        "year": 2025,
        "period": "M08"
      },
      {
        "date": "2025-07-27",
        "value": 2400000.0,
        "year": 2025,
        "period": "M07"
      },
      {
        "date": "2025-06-27",
        "value": 2550000.0,
        "year": 2025,
        "period": "M06"
      },
      {
        "date": "2025-05-28",
        "value": 2700000.0,
        "year": 2025,
        "period": "M05"
      },
      {
        "date": "2025-04-28",
        "value": 2850000.0,
        "year": 2025,
        "period": "M04"
      },
      {
        "date": "2025-03-29",
        "value": 3000000.0,
        "year": 2025,
        "period": "M03"
      },
      {
        "date": "2025-02-27",
        "value": 3150000.0,
        "year": 2025,
        "period": "M02"
      },
      {
        "date": "2025-01-28",
        "value": 3300000.0000000005,
        "year": 2025,
        "period": "M01"
      },
      {
        "date": "2024-12-29",
        "value": 3449999.9999999995,
        "year": 2024,
        "period": "M12"
      },
      {
        "date": "2024-11-29",
        "value": 3600000.0,
        "year": 2024,
        "period": "M11"
      },
      {
        "date": "2024-10-30",
        "value": 3750000.0,
        "year": 2024,
        "period": "M10"
      },
      {
        "date": "2024-09-30",
        "value": 2100000.0,
        "year": 2024,
        "period": "M09"
      },
      {
        "date": "2024-08-31",
        "value": 2250000.0,
        "year": 2024,
        "period": "M08"
      },
      {
        "date": "2024-08-01",
        "value": 2400000.0,
        "year": 2024,
        "period": "M08"
      },
      {
        "date": "2024-07-02",
        "value": 2550000.0,
        "year": 2024,
        "period": "M07"
      },
      {
        "date": "2024-06-02",
        "value": 2700000.0,
        "year": 2024,
        "period": "M06"
      },
      {
        "date": "2024-05-03",
        "value": 2850000.0,
        "year": 2024,
        "period": "M05"
      },
      {
        "date": "2024-04-03",
        "value": 3000000.0,
        "year": 2024,
        "period": "M04"
      },
      {
        "date": "2024-03-04",
        "value": 3150000.0,
        "year": 2024,
        "period": "M03"
      },
      {
        "date": "2024-02-03",
        "value": 3300000.0000000005,
        "year": 2024,
        "period": "M02"
      },
      {
        "date": "2024-01-04",
        "value": 3449999.9999999995,
        "year": 2024,
        "period": "M01"
      },
      {
        "date": "2023-12-05",
        "value": 3600000.0,
        "year": 2023,
        "period": "M12"
      },
      {
        "date": "2023-11-05",
        "value": 3750000.0,
        "year": 2023,
        "period": "M11"
      }
    ],
    "UE": [
      {
        "date": "2025-09-25",
        "value": 1260000.0,
        "year": 2025,
        "period": "M09"
      },
      {
        "date": "2025-08-26",
        "value": 1350000.0,
        "year": 2025,
        "period": "M08"
      },
      {
        "date": "2025-07-27",
        "value": 1440000.0,
        "year": 2025,
        "period": "M07"
      },
      {
        "date": "2025-06-27",
        "value": 1530000.0,
        "year": 2025,
        "period": "M06"
      },
      {
        "date": "2025-05-28",
        "value": 1620000.0,
        "year": 2025,
        "period": "M05"
      },
      {
        "date": "2025-04-28",
        "value": 1710000.0,
        "year": 2025,
        "period": "M04"
      },
      {
        "date": "2025-03-29",
        "value": 1800000.0,
        "year": 2025,
        "period": "M03"
      },
      {
        "date": "2025-02-27",
        "value": 1890000.0,
        "year": 2025,
        "period": "M02"
      },
      {
        "date": "2025-01-28",
        "value": 1980000.0000000002,
        "year": 2025,
        "period": "M01"
      },
      {
        "date": "2024-12-29",
        "value": 2069999.9999999998,
        "year": 2024,
        "period": "M12"
      },
      {
        "date": "2024-11-29",
        "value": 2160000.0,
        "year": 2024,
        "period": "M11"
      },
      {
        "date": "2024-10-30",
        "value": 2250000.0,
        "year": 2024,
        "period": "M10"
      },
      {
        "date": "2024-09-30",
        "value": 1260000.0,
        "year": 2024,
        "period": "M09"
      },
      {
        "date": "2024-08-31",
        "value": 1350000.0,
        "year": 2024,
        "period": "M08"
      },
      {
        "date": "2024-08-01",
        "value": 1440000.0,
        "year": 2024,
        "period": "M08"
      },
      {
        "date": "2024-07-02",
        "value": 1530000.0,
        "year": 2024,
        "period": "M07"
      },
      {
        "date": "2024-06-02",
        "value": 1620000.0,
        "year": 2024,
        "period": "M06"
      },
      {
        "date": "2024-05-03",
        "value": 1710000.0,
        "year": 2024,
        "period": "M05"
      },
      {
        "date": "2024-04-03",
        "value": 1800000.0,
        "year": 2024,
        "period": "M04"
      },
      {
        "date": "2024-03-04",
        "value": 1890000.0,
        "year": 2024,
        "period": "M03"
      },
      {
        "date": "2024-02-03",
        "value": 1980000.0000000002,
        "year": 2024,
        "period": "M02"
      },
      {
        "date": "2024-01-04",
        "value": 2069999.9999999998,
        "year": 2024,
        "period": "M01"
      },
      {
        "date": "2023-12-05",
        "value": 2160000.0,
        "year": 2023,
        "period": "M12"
      },
      {
        "date": "2023-11-05",
        "value": 2250000.0,
        "year": 2023,
        "period": "M11"
      }
    ],
    "UU": [
      {
        "date": "2025-09-25",
        "value": 1050000.0,
        "year": 2025,
        "period": "M09"
      },
      {
        "date": "2025-08-26",
        "value": 1125000.0,
        "year": 2025,
        "period": "M08"
      },
      {
        "date": "2025-07-27",
        "value": 1200000.0,
        "year": 2025,
        "period": "M07"
      },
      {
        "date": "2025-06-27",
        "value": 1275000.0,
        "year": 2025,
        "period": "M06"
      },
      {
        "date": "2025-05-28",
        "value": 1350000.0,
        "year": 2025,
        "period": "M05"
      },
      {
        "date": "2025-04-28",
        "value": 1425000.0,
        "year": 2025,
        "period": "M04"
      },
      {
        "date": "2025-03-29",
        "value": 1500000.0,
        "year": 2025,
        "period": "M03"
      },
      {
        "date": "2025-02-27",
        "value": 1575000.0,
        "year": 2025,
        "period": "M02"
      },
      {
        "date": "2025-01-28",
        "value": 1650000.0000000002,
        "year": 2025,
        "period": "M01"
      },
      {
        "date": "2024-12-29",
        "value": 1724999.9999999998,
        "year": 2024,
        "period": "M12"
      },
      {
        "date": "2024-11-29",
        "value": 1800000.0,
        "year": 2024,
        "period": "M11"
      },
      {
        "date": "2024-10-30",
        "value": 1875000.0,
        "year": 2024,
        "period": "M10"
      },
      {
        "date": "2024-09-30",
        "value": 1050000.0,
        "year": 2024,
        "period": "M09"
      },
      {
        "date": "2024-08-31",
        "value": 1125000.0,
        "year": 2024,
        "period": "M08"
      },
      {
        "date": "2024-08-01",
        "value": 1200000.0,
        "year": 2024,
        "period": "M08"
      },
      {
        "date": "2024-07-02",
        "value": 1275000.0,
        "year": 2024,
        "period": "M07"
      },
      {
        "date": "2024-06-02",
        "value": 1350000.0,
        "year": 2024,
        "period": "M06"
      },
      {
        "date": "2024-05-03",
        "value": 1425000.0,
        "year": 2024,
        "period": "M05"
      },
      {
        "date": "2024-04-03",
        "value": 1500000.0,
        "year": 2024,
        "period": "M04"
      },
      {
        "date": "2024-03-04",
        "value": 1575000.0,
        "year": 2024,
        "period": "M03"
      },
      {
        "date": "2024-02-03",
        "value": 1650000.0000000002,
        "year": 2024,
        "period": "M02"
      },
      {
        "date": "2024-01-04",
        "value": 1724999.9999999998,
        "year": 2024,
        "period": "M01"
      },
      {
        "date": "2023-12-05",
        "value": 1800000.0,
        "year": 2023,
        "period": "M12"
      },
      {
        "date": "2023-11-05",
        "value": 1875000.0,
        "year": 2023,
        "period": "M11"
      }
    ],
    "UN": [
      {
        "date": "2025-09-25",
        "value": 560000.0,
        "year": 2025,
        "period": "M09"
      },
      {
        "date": "2025-08-26",
        "value": 600000.0,
        "year": 2025,
        "period": "M08"
      },
      {
        "date": "2025-07-27",
        "value": 640000.0,
        "year": 2025,
        "period": "M07"
      },
      {
        "date": "2025-06-27",
        "value": 680000.0,
        "year": 2025,
        "period": "M06"
      },
      {
        "date": "2025-05-28",
        "value": 720000.0,
        "year": 2025,
        "period": "M05"
      },
      {
        "date": "2025-04-28",
        "value": 760000.0,
        "year": 2025,
        "period": "M04"
      },
      {
        "date": "2025-03-29",
        "value": 800000.0,
        "year": 2025,
        "period": "M03"
      },
      {
        "date": "2025-02-27",
        "value": 840000.0,
        "year": 2025,
        "period": "M02"
      },
      {
        "date": "2025-01-28",
        "value": 880000.0000000001,
        "year": 2025,
        "period": "M01"
      },
      {
        "date": "2024-12-29",
        "value": 919999.9999999999,
        "year": 2024,
        "period": "M12"
      },
      {
        "date": "2024-11-29",
        "value": 960000.0,
        "year": 2024,
        "period": "M11"
      },
      {
        "date": "2024-10-30",
        "value": 1000000.0,
        "year": 2024,
        "period": "M10"
      },
      {
        "date": "2024-09-30",
        "value": 560000.0,
        "year": 2024,
        "period": "M09"
      },
      {
        "date": "2024-08-31",
        "value": 600000.0,
        "year": 2024,
        "period": "M08"
      },
      {
        "date": "2024-08-01",
        "value": 640000.0,
        "year": 2024,
        "period": "M08"
      },
      {
        "date": "2024-07-02",
        "value": 680000.0,
        "year": 2024,
        "period": "M07"
      },
      {
        "date": "2024-06-02",
        "value": 720000.0,
        "year": 2024,
        "period": "M06"
      },
      {
        "date": "2024-05-03",
        "value": 760000.0,
        "year": 2024,
        "period": "M05"
      },
      {
        "date": "2024-04-03",
        "value": 800000.0,
        "year": 2024,
        "period": "M04"
      },
      {
        "date": "2024-03-04",
        "value": 840000.0,
        "year": 2024,
        "period": "M03"
      },
      {
        "date": "2024-02-03",
        "value": 880000.0000000001,
        "year": 2024,
        "period": "M02"
      },
      {
        "date": "2024-01-04",
        "value": 919999.9999999999,
        "year": 2024,
        "period": "M01"
      },
      {
        "date": "2023-12-05",
        "value": 960000.0,
        "year": 2023,
        "period": "M12"
      },
      {
        "date": "2023-11-05",
        "value": 1000000.0,
        "year": 2023,
        "period": "M11"
      }
    ],
    "NE": [
      {
        "date": "2025-09-25",
        "value": 1750000.0,
        "year": 2025,
        "period": "M09"
      },
      {
        "date": "2025-08-26",
        "value": 1875000.0,
        "year": 2025,
        "period": "M08"
      },
      {
        "date": "2025-07-27",
        "value": 2000000.0,
        "year": 2025,
        "period": "M07"
      },
      {
        "date": "2025-06-27",
        "value": 2125000.0,
        "year": 2025,
        "period": "M06"
      },
      {
        "date": "2025-05-28",
        "value": 2250000.0,
        "year": 2025,
        "period": "M05"
      },
      {
        "date": "2025-04-28",
        "value": 2375000.0,
        "year": 2025,
        "period": "M04"
      },
      {
        "date": "2025-03-29",
        "value": 2500000.0,
        "year": 2025,
        "period": "M03"
      },
      {
        "date": "2025-02-27",
        "value": 2625000.0,
        "year": 2025,
        "period": "M02"
      },
      {
        "date": "2025-01-28",
        "value": 2750000.0,
        "year": 2025,
        "period": "M01"
      },
      {
        "date": "2024-12-29",
        "value": 2875000.0,
        "year": 2024,
        "period": "M12"
      },
      {
        "date": "2024-11-29",
        "value": 3000000.0,
        "year": 2024,
        "period": "M11"
      },
      {
        "date": "2024-10-30",
        "value": 3125000.0,
        "year": 2024,
        "period": "M10"
      },
      {
        "date": "2024-09-30",
        "value": 1750000.0,
        "year": 2024,
        "period": "M09"
      },
      {
        "date": "2024-08-31",
        "value": 1875000.0,
        "year": 2024,
        "period": "M08"
      },
      {
        "date": "2024-08-01",
        "value": 2000000.0,
        "year": 2024,
        "period": "M08"
      },
      {
        "date": "2024-07-02",
        "value": 2125000.0,
        "year": 2024,
        "period": "M07"
      },
      {
        "date": "2024-06-02",
        "value": 2250000.0,
        "year": 2024,
        "period": "M06"
      },
      {
        "date": "2024-05-03",
        "value": 2375000.0,
        "year": 2024,
        "period": "M05"
      },
      {
        "date": "2024-04-03",
        "value": 2500000.0,
        "year": 2024,
        "period": "M04"
      },
      {
        "date": "2024-03-04",
        "value": 2625000.0,
        "year": 2024,
        "period": "M03"
      },
      {
        "date": "2024-02-03",
        "value": 2750000.0,
        "year": 2024,
        "period": "M02"
      },
      {
        "date": "2024-01-04",
        "value": 2875000.0,
        "year": 2024,
        "period": "M01"
      },
      {
        "date": "2023-12-05",
        "value": 3000000.0,
        "year": 2023,
        "period": "M12"
      },
      {
        "date": "2023-11-05",
        "value": 3125000.0,
        "year": 2023,
        "period": "M11"
      }
    ],
    "NU": [
      {
        "date": "2025-09-25",
        "value": 280000.0,
        "year": 2025,
        "period": "M09"
      },
      {
        "date": "2025-08-26",
        "value": 300000.0,
        "year": 2025,
        "period": "M08"
      },
      {
        "date": "2025-07-27",
        "value": 320000.0,
        "year": 2025,
        "period": "M07"
      },
      {
        "date": "2025-06-27",
        "value": 340000.0,
        "year": 2025,
        "period": "M06"
      },
      {
        "date": "2025-05-28",
        "value": 360000.0,
        "year": 2025,
        "period": "M05"
      },
      {
        "date": "2025-04-28",
        "value": 380000.0,
        "year": 2025,
        "period": "M04"
      },
      {
        "date": "2025-03-29",
        "value": 400000.0,
        "year": 2025,
        "period": "M03"
      },
      {
        "date": "2025-02-27",
        "value": 420000.0,
        "year": 2025,
        "period": "M02"
      },
      {
        "date": "2025-01-28",
        "value": 440000.00000000006,
        "year": 2025,
        "period": "M01"
      },
      {
        "date": "2024-12-29",
        "value": 459999.99999999994,
        "year": 2024,
        "period": "M12"
      },
      {
        "date": "2024-11-29",
        "value": 480000.0,
        "year": 2024,
        "period": "M11"
      },
      {
        "date": "2024-10-30",
        "value": 500000.0,
        "year": 2024,
        "period": "M10"
      },
      {
        "date": "2024-09-30",
        "value": 280000.0,
        "year": 2024,
        "period": "M09"
      },
      {
        "date": "2024-08-31",
        "value": 300000.0,
        "year": 2024,
        "period": "M08"
      },
      {
        "date": "2024-08-01",
        "value": 320000.0,
        "year": 2024,
        "period": "M08"
      },
      {
        "date": "2024-07-02",
        "value": 340000.0,
        "year": 2024,
        "period": "M07"
      },
      {
        "date": "2024-06-02",
        "value": 360000.0,
        "year": 2024,
        "period": "M06"
      },
      {
        "date": "2024-05-03",
        "value": 380000.0,
        "year": 2024,
        "period": "M05"
      },
      {
        "date": "2024-04-03",
        "value": 400000.0,
        "year": 2024,
        "period": "M04"
      },
      {
        "date": "2024-03-04",
        "value": 420000.0,
        "year": 2024,
        "period": "M03"
      },
      {
        "date": "2024-02-03",
        "value": 440000.00000000006,
        "year": 2024,
        "period": "M02"
      },
      {
        "date": "2024-01-04",
        "value": 459999.99999999994,
        "year": 2024,
        "period": "M01"
      },
      {
        "date": "2023-12-05",
        "value": 480000.0,
        "year": 2023,
        "period": "M12"
      },
      {
        "date": "2023-11-05",
        "value": 500000.0,
        "year": 2023,
        "period": "M11"
      }
    ],
    "NN": [
      {
        "date": "2025-09-25",
        "value": 66499999.99999999,
        "year": 2025,
        "period": "M09"
      },
      {
        "date": "2025-08-26",
        "value": 71250000.0,
        "year": 2025,
        "period": "M08"
      },
      {
        "date": "2025-07-27",
        "value": 76000000.0,
        "year": 2025,
        "period": "M07"
      },
      {
        "date": "2025-06-27",
        "value": 80750000.0,
        "year": 2025,
        "period": "M06"
      },
      {
        "date": "2025-05-28",
        "value": 85500000.0,
        "year": 2025,
        "period": "M05"
      },
      {
        "date": "2025-04-28",
        "value": 90250000.0,
        "year": 2025,
        "period": "M04"
      },
      {
        "date": "2025-03-29",
        "value": 95000000.0,
        "year": 2025,
        "period": "M03"
      },
      {
        "date": "2025-02-27",
        "value": 99750000.0,
        "year": 2025,
        "period": "M02"
      },
      {
        "date": "2025-01-28",
        "value": 104500000.00000001,
        "year": 2025,
        "period": "M01"
      },
      {
        "date": "2024-12-29",
        "value": 109249999.99999999,
        "year": 2024,
        "period": "M12"
      },
      {
        "date": "2024-11-29",
        "value": 114000000.0,
        "year": 2024,
        "period": "M11"
      },
      {
        "date": "2024-10-30",
        "value": 118750000.0,
        "year": 2024,
        "period": "M10"
      },
      {
        "date": "2024-09-30",
        "value": 66499999.99999999,
        "year": 2024,
        "period": "M09"
      },
      {
        "date": "2024-08-31",
        "value": 71250000.0,
        "year": 2024,
        "period": "M08"
      },
      {
        "date": "2024-08-01",
        "value": 76000000.0,
        "year": 2024,
        "period": "M08"
      },
      {
        "date": "2024-07-02",
        "value": 80750000.0,
        "year": 2024,
        "period": "M07"
      },
      {
        "date": "2024-06-02",
        "value": 85500000.0,
        "year": 2024,
        "period": "M06"
      },
      {
        "date": "2024-05-03",
        "value": 90250000.0,
        "year": 2024,
        "period": "M05"
      },
      {
        "date": "2024-04-03",
        "value": 95000000.0,
        "year": 2024,
        "period": "M04"
      },
      {
        "date": "2024-03-04",
        "value": 99750000.0,
        "year": 2024,
        "period": "M03"
      },
      {
        "date": "2024-02-03",
        "value": 104500000.00000001,
        "year": 2024,
        "period": "M02"
      },
      {
        "date": "2024-01-04",
        "value": 109249999.99999999,
        "year": 2024,
        "period": "M01"
      },
      {
        "date": "2023-12-05",
        "value": 114000000.0,
        "year": 2023,
        "period": "M12"
      },
      {
        "date": "2023-11-05",
        "value": 118750000.0,
        "year": 2023,
        "period": "M11"
      }
    ]
  },
  "key_metrics": {
    "job_finding_rate": 0.43902439024390244,
    "job_separation_rate": 0.013333333333333334,
    "net_flows": {
      "net_employment_growth": -490000.0,
      "net_unemployment_change": -140000.0,
      "net_labor_force_participation": -630000.0
    }
  },
  "analysis_summary": {
    "total_flows_analyzed": 9,
    "data_quality": "High",
    "latest_data_date": "2025-09-25"
  }
}